{"rules":[{"name":"new rule","base":{"width":2,"height":1,"contents":[[{"One":1},"None"],[{"One":0},{"One":2}]]},"enabled":true,"flip_x":false,"flip_y":false,"rotate":true,"failrate":0},{"name":"sideways","base":{"width":2,"height":1,"contents":[[{"Group":0},{"One":0}],[{"One":0},{"Copy":[0,0]}]]},"enabled":true,"flip_x":true,"flip_y":false,"rotate":false,"failrate":164},{"name":"up","base":{"width":1,"height":2,"contents":[[{"One":0},{"Copy":[0,1]}],[{"Group":0},"None"]]},"enabled":true,"flip_x":false,"flip_y":false,"rotate":false,"failrate":0},{"name":"new rule","base":{"width":1,"height":1,"contents":[[{"One":2},{"One":3}]]},"enabled":true,"flip_x":false,"flip_y":false,"rotate":false,"failrate":0},{"name":"new rule","base":{"width":1,"height":1,"contents":[[{"One":3},{"One":4}]]},"enabled":true,"flip_x":false,"flip_y":false,"rotate":false,"failrate":0},{"name":"new rule","base":{"width":1,"height":1,"contents":[[{"One":4},{"One":5}]]},"enabled":true,"flip_x":false,"flip_y":false,"rotate":false,"failrate":0},{"name":"new rule","base":{"width":1,"height":1,"contents":[[{"One":5},{"One":0}]]},"enabled":true,"flip_x":false,"flip_y":false,"rotate":false,"failrate":0},{"name":"new rule","base":{"width":1,"height":1,"contents":[[{"One":5},{"One":0}]]},"enabled":true,"flip_x":false,"flip_y":false,"rotate":false,"failrate":0}],"types":[{"name":"air","color":[0,0,0]},{"name":"source","color":[255,255,255]},{"name":"cell #2","color":[255,216,44]},{"name":"cell #3","color":[254,131,0]},{"name":"cell #4","color":[255,73,3]},{"name":"cell #5","color":[255,8,0]}],"groups":[{"name":"fire","void":false,"cells":[5,4,3,2]}]}